{
  "club": {
    "id": "coventry",
    "name": "Coventry City",
    "slug": "coventry",
    "country": "Inglaterra",
    "league": "Premier League",
    "city": "Coventry",
    "stadium": "Coventry Building Society Arena",
    "coach": "Frank Lampard",
    "founded": 1883,
    "primaryColor": "#77BEE9"
  },
  "players": [
    {
      "id": "oliver-dovin",
      "name": "Oliver Dovin",
      "slug": "oliver-dovin",
      "birthDate": "2002-07-11",
      "nationality": "Suecia",
      "position": "Portero",
      "height": 187,
      "dominantFoot": "Derecho",
      "marketValue": 4,
      "contractUntil": "2028-06-30",
      "shirtNumber": 1,
      "status": "titular"
    },
    {
      "id": "milan-van-ewijk",
      "name": "Milan van Ewijk",
      "slug": "milan-van-ewijk",
      "birthDate": "2000-09-08",
      "nationality": "Países Bajos",
      "position": "Lateral derecho",
      "height": 175,
      "dominantFoot": "Derecho",
      "marketValue": 8,
      "contractUntil": "2028-06-30",
      "shirtNumber": 27,
      "status": "titular"
    },
    {
      "id": "bobby-thomas",
      "name": "Bobby Thomas",
      "slug": "bobby-thomas",
      "birthDate": "2001-01-30",
      "nationality": "Inglaterra",
      "position": "Defensa central",
      "height": 186,
      "dominantFoot": "Derecho",
      "marketValue": 7,
      "contractUntil": "2027-06-30",
      "shirtNumber": 4,
      "status": "titular"
    },
    {
      "id": "luis-binks",
      "name": "Luis Binks",
      "slug": "luis-binks",
      "birthDate": "2001-09-02",
      "nationality": "Inglaterra",
      "position": "Defensa central",
      "height": 188,
      "dominantFoot": "Izquierdo",
      "marketValue": 4,
      "contractUntil": "2028-06-30",
      "shirtNumber": 2,
      "status": "suplente"
    },
    {
      "id": "liam-kitching",
      "name": "Liam Kitching",
      "slug": "liam-kitching",
      "birthDate": "1999-09-25",
      "nationality": "Inglaterra",
      "position": "Defensa central",
      "height": 191,
      "dominantFoot": "Izquierdo",
      "marketValue": 4,
      "contractUntil": "2027-06-30",
      "shirtNumber": 15,
      "status": "suplente"
    },
    {
      "id": "jay-dasilva",
      "name": "Jay Dasilva",
      "slug": "jay-dasilva",
      "birthDate": "1998-04-22",
      "nationality": "Inglaterra",
      "position": "Lateral izquierdo",
      "height": 170,
      "dominantFoot": "Izquierdo",
      "marketValue": 2.5,
      "contractUntil": "2027-06-30",
      "shirtNumber": 3,
      "status": "suplente"
    },
    {
      "id": "ben-sheaf",
      "name": "Ben Sheaf",
      "slug": "ben-sheaf",
      "birthDate": "1998-02-05",
      "nationality": "Inglaterra",
      "position": "Mediocentro defensivo",
      "height": 185,
      "dominantFoot": "Derecho",
      "marketValue": 10,
      "contractUntil": "2028-06-30",
      "shirtNumber": 14,
      "status": "titular"
    },
    {
      "id": "jack-rudoni",
      "name": "Jack Rudoni",
      "slug": "jack-rudoni",
      "birthDate": "2001-06-14",
      "nationality": "Inglaterra",
      "position": "Mediapunta",
      "height": 185,
      "dominantFoot": "Izquierdo",
      "marketValue": 8,
      "contractUntil": "2028-06-30",
      "shirtNumber": 5,
      "status": "titular"
    },
    {
      "id": "jamie-allen",
      "name": "Jamie Allen",
      "slug": "jamie-allen",
      "birthDate": "1995-01-29",
      "nationality": "Inglaterra",
      "position": "Mediocentro",
      "height": 180,
      "dominantFoot": "Derecho",
      "marketValue": 2,
      "contractUntil": "2027-06-30",
      "shirtNumber": 8,
      "status": "suplente"
    },
    {
      "id": "ephron-mason-clark",
      "name": "Ephron Mason-Clark",
      "slug": "ephron-mason-clark",
      "birthDate": "1999-08-25",
      "nationality": "Inglaterra",
      "position": "Extremo izquierdo",
      "height": 178,
      "dominantFoot": "Derecho",
      "marketValue": 5,
      "contractUntil": "2028-06-30",
      "shirtNumber": 10,
      "status": "titular"
    },
    {
      "id": "haji-wright",
      "name": "Haji Wright",
      "slug": "haji-wright",
      "birthDate": "1998-03-27",
      "nationality": "Estados Unidos",
      "position": "Delantero centro",
      "height": 193,
      "dominantFoot": "Derecho",
      "marketValue": 12,
      "contractUntil": "2028-06-30",
      "shirtNumber": 11,
      "status": "titular"
    },
    {
      "id": "brandon-thomas-asante",
      "name": "Brandon Thomas-Asante",
      "slug": "brandon-thomas-asante",
      "birthDate": "1998-12-29",
      "nationality": "Ghana",
      "position": "Delantero centro",
      "height": 180,
      "dominantFoot": "Derecho",
      "marketValue": 5,
      "contractUntil": "2028-06-30",
      "shirtNumber": 23,
      "status": "suplente"
    }
  ]
}
