{
  "club": {
    "id": "nottingham-forest",
    "name": "Nottingham Forest",
    "slug": "nottingham-forest",
    "country": "Inglaterra",
    "league": "Premier League",
    "city": "Nottingham",
    "stadium": "City Ground",
    "coach": "Sean Dyche",
    "founded": 1865,
    "primaryColor": "#DD0000"
  },
  "players": [
    { "id": "matz-sels", "name": "Matz Sels", "slug": "matz-sels", "birthDate": "1992-02-26", "nationality": "Bélgica", "position": "Portero", "height": 188, "dominantFoot": "Derecho", "marketValue": 12, "contractUntil": "2027-06-30", "shirtNumber": 26, "status": "titular" },
    { "id": "ola-aina", "name": "Ola Aina", "slug": "ola-aina", "birthDate": "1996-10-08", "nationality": "Nigeria", "position": "Lateral derecho", "height": 184, "dominantFoot": "Derecho", "marketValue": 15, "contractUntil": "2027-06-30", "shirtNumber": 34, "status": "titular" },
    { "id": "murillo", "name": "Murillo", "slug": "murillo", "birthDate": "2002-07-03", "nationality": "Brasil", "position": "Defensa central", "height": 182, "dominantFoot": "Izquierdo", "marketValue": 45, "contractUntil": "2029-06-30", "shirtNumber": 40, "status": "titular" },
    { "id": "nikola-milenkovic", "name": "Nikola Milenković", "slug": "nikola-milenkovic", "birthDate": "1997-10-12", "nationality": "Serbia", "position": "Defensa central", "height": 195, "dominantFoot": "Derecho", "marketValue": 25, "contractUntil": "2028-06-30", "shirtNumber": 4, "status": "titular" },
    { "id": "neco-williams", "name": "Neco Williams", "slug": "neco-williams", "birthDate": "2001-04-13", "nationality": "Gales", "position": "Lateral izquierdo", "height": 183, "dominantFoot": "Derecho", "marketValue": 20, "contractUntil": "2028-06-30", "shirtNumber": 7, "status": "titular" },
    { "id": "morato", "name": "Morato", "slug": "morato", "birthDate": "2001-01-08", "nationality": "Brasil", "position": "Defensa central", "height": 188, "dominantFoot": "Izquierdo", "marketValue": 12, "contractUntil": "2029-06-30", "shirtNumber": 6, "status": "suplente" },
    { "id": "elliot-anderson", "name": "Elliot Anderson", "slug": "elliot-anderson", "birthDate": "2002-11-06", "nationality": "Inglaterra", "position": "Mediocentro", "height": 180, "dominantFoot": "Derecho", "marketValue": 40, "contractUntil": "2029-06-30", "shirtNumber": 8, "status": "titular" },
    { "id": "ibrahim-sangare", "name": "Ibrahim Sangaré", "slug": "ibrahim-sangare", "birthDate": "1997-12-02", "nationality": "Costa de Marfil", "position": "Mediocentro defensivo", "height": 191, "dominantFoot": "Derecho", "marketValue": 18, "contractUntil": "2028-06-30", "shirtNumber": 5, "status": "titular" },
    { "id": "douglas-luiz", "name": "Douglas Luiz", "slug": "douglas-luiz", "birthDate": "1998-05-09", "nationality": "Brasil", "position": "Mediocentro", "height": 178, "dominantFoot": "Derecho", "marketValue": 25, "contractUntil": "2028-06-30", "shirtNumber": 16, "status": "suplente" },
    { "id": "morgan-gibbs-white", "name": "Morgan Gibbs-White", "slug": "morgan-gibbs-white", "birthDate": "2000-01-27", "nationality": "Inglaterra", "position": "Mediapunta", "height": 171, "dominantFoot": "Derecho", "marketValue": 50, "contractUntil": "2028-06-30", "shirtNumber": 10, "status": "titular" },
    { "id": "callum-hudson-odoi", "name": "Callum Hudson-Odoi", "slug": "callum-hudson-odoi", "birthDate": "2000-11-14", "nationality": "Inglaterra", "position": "Extremo izquierdo", "height": 177, "dominantFoot": "Derecho", "marketValue": 22, "contractUntil": "2027-06-30", "shirtNumber": 14, "status": "titular" },
    { "id": "dan-ndoye", "name": "Dan Ndoye", "slug": "dan-ndoye", "birthDate": "2000-10-25", "nationality": "Suiza", "position": "Extremo derecho", "height": 184, "dominantFoot": "Derecho", "marketValue": 30, "contractUntil": "2030-06-30", "shirtNumber": 20, "status": "titular" },
    { "id": "chris-wood", "name": "Chris Wood", "slug": "chris-wood", "birthDate": "1991-12-07", "nationality": "Nueva Zelanda", "position": "Delantero centro", "height": 191, "dominantFoot": "Derecho", "marketValue": 12, "contractUntil": "2027-06-30", "shirtNumber": 11, "status": "titular" },
    { "id": "igor-jesus", "name": "Igor Jesus", "slug": "igor-jesus", "birthDate": "2001-02-04", "nationality": "Brasil", "position": "Delantero centro", "height": 187, "dominantFoot": "Derecho", "marketValue": 18, "contractUntil": "2029-06-30", "shirtNumber": 9, "status": "suplente" }
  ]
}
